Metadata-Version: 2.1
Name: thesaurus-generator
Version: 0.0.6
Summary: An automatic thesaurus generator.
Home-page: https://github.com/pegondo/thesaurus_generator
Download-URL: https://github.com/pegondo/thesaurus_generator/archive/refs/tags/0.0.6.tar.gz
Author: José Alonso González
Author-email: pegondo99@gmail.com
License: MIT
Keywords: thesaurus,generation,automatic,nlp
Classifier: Development Status :: 3 - Alpha
Classifier: Intended Audience :: Developers
Classifier: Topic :: Software Development :: Build Tools
Classifier: License :: OSI Approved :: MIT License
Classifier: Programming Language :: Python :: 3.9
License-File: LICENSE.txt
